davinci_functions/__init__.py
davinci_functions/_explain.py
davinci_functions/_function.py
davinci_functions/_judge.py
davinci_functions/_list.py
davinci_functions/_version.py
davinci_functions-0.1.4.dist-info/METADATA
davinci_functions-0.1.4.dist-info/WHEEL
davinci_functions-0.1.4.dist-info/licenses/LICENSE
davinci_functions-0.1.4.dist-info/RECORD
