Metadata-Version: 2.1
Name: davinci-functions
Version: 0.1.4
Summary: Library to ask OpenAI GPT for generating objects on the Python runtime.
Project-URL: Homepage, https://github.com/odashi/davinci-functions
Project-URL: Bug Tracker, https://github.com/odashi/davinci-functions/issues
Author-email: Yusuke Oda <odashi@inspiredco.ai>
License: MIT License
License-File: LICENSE
Keywords: cloud storage,gcloud,google,google cloud,storage
Classifier: License :: OSI Approved :: MIT License
Classifier: Programming Language :: Python :: 3.8
Classifier: Programming Language :: Python :: 3.9
Classifier: Programming Language :: Python :: 3.10
Classifier: Programming Language :: Python :: 3.11
Requires-Python: <3.12,>=3.8
Requires-Dist: dill>=0.3.6
Requires-Dist: openai>=0.27.0
Provides-Extra: dev
Requires-Dist: black>=22.10; extra == 'dev'
Requires-Dist: flake8>=5.0; extra == 'dev'
Requires-Dist: isort>=5.10; extra == 'dev'
Requires-Dist: mypy>=0.991; extra == 'dev'
Requires-Dist: pyproject-flake8>=5.0; extra == 'dev'
Requires-Dist: pytest-mock>=3.10.0; extra == 'dev'
Requires-Dist: pytest>=7.1; extra == 'dev'
Provides-Extra: mypy
Requires-Dist: mypy>=0.991; extra == 'mypy'
Requires-Dist: pytest-mock>=3.10.0; extra == 'mypy'
Requires-Dist: pytest>=7.1; extra == 'mypy'
